seating_planner/__init__.py
seating_planner/model.py
seating_planner/visualizations.py
seating_planner-0.1.8.dist-info/LICENSE
seating_planner-0.1.8.dist-info/METADATA
seating_planner-0.1.8.dist-info/WHEEL
seating_planner-0.1.8.dist-info/top_level.txt
seating_planner-0.1.8.dist-info/RECORD
