Metadata-Version: 2.1
Name: seating-planner
Version: 0.1.8
Summary: A package for optimizing seating arrangements
Home-page: https://github.com/koftezz/seating-planner
Author-email: Zeynel Batuhan Organ <batuhan.organ@ozu.edu.tr>
Classifier: Programming Language :: Python :: 3
Classifier: License :: OSI Approved :: MIT License
Classifier: Operating System :: OS Independent
Requires-Python: >=3.9
License-File: LICENSE
Requires-Dist: pulp>=2.7.0
Requires-Dist: pandas>=1.3.0
Requires-Dist: altair>=5.0.0
Requires-Dist: highspy>=1.5.1
Requires-Dist: numpy>=1.21.0
